sfcparse/__init__.py
sfcparse/error.py
sfcparse/__hash/comparefilehash.py
sfcparse/__hash/createfilehash.py
sfcparse/__ini/inibuildauto.py
sfcparse/__ini/inibuildmanual.py
sfcparse/__ini/iniexportfile.py
sfcparse/__ini/iniimportfile.py
sfcparse/__json/jsonexportfile.py
sfcparse/__json/jsonexportstr.py
sfcparse/__json/jsonimportfile.py
sfcparse/__json/jsonimportstr.py
sfcparse/__native/appendfile.py
sfcparse/__native/builddata.py
sfcparse/__native/cleanformat.py
sfcparse/__native/exportfile.py
sfcparse/__native/importattrs.py
sfcparse/__native/importfile.py
sfcparse/__native/importfileraw.py
sfcparse/__native/savefile.py
sfcparse/__xml/xmlbuildmanual.py
sfcparse/__xml/xmlexportfile.py
sfcparse/__xml/xmlexportstr.py
sfcparse/__xml/xmlimportfile.py
sfcparse/__xml/xmlimportstr.py
sfcparse/__yaml/yamlexportfile.py
sfcparse/__yaml/yamlexportstr.py
sfcparse/__yaml/yamlimportfile.py
sfcparse/__yaml/yamlimportstr.py
sfcparse-2.0.0.dist-info/METADATA
sfcparse-2.0.0.dist-info/WHEEL
sfcparse-2.0.0.dist-info/top_level.txt
sfcparse-2.0.0.dist-info/RECORD
