Metadata-Version: 2.1
Name: sfcparse
Version: 2.0.0
Summary: The easy to use library for your data, configuration, and save files
Home-page: https://github.com/aaronater10/sfcparse
Author: aaronater10
Author-email: dev_admin@dunnts.com
License: MIT
Keywords: python,py,config,file,export,parse,text file,cfg,conf,save file,config file,sfcparse,aaronater10,db,database,simple,configuration,alternative,safe,ini,json,xml,yml,data,import
Classifier: Development Status :: 5 - Production/Stable
Classifier: Intended Audience :: Developers
Classifier: Programming Language :: Python :: 3
Classifier: Programming Language :: Python :: 3.6
Classifier: Programming Language :: Python :: 3.7
Classifier: Programming Language :: Python :: 3.8
Classifier: Programming Language :: Python :: 3.9
Classifier: Programming Language :: Python :: 3.10
Classifier: Operating System :: POSIX :: Linux
Classifier: Operating System :: Microsoft :: Windows
Classifier: Operating System :: MacOS :: MacOS X
Requires-Dist: PyYAML (>=5.4.1)
